setup.py
django_inline_orderable.egg-info/PKG-INFO
django_inline_orderable.egg-info/SOURCES.txt
django_inline_orderable.egg-info/dependency_links.txt
django_inline_orderable.egg-info/top_level.txt
inline_orderable/__init__.py
inline_orderable/admin.py
inline_orderable/models.py