Metadata-Version: 1.1
Name: django-inline-orderable
Version: 0.1.1
Summary: An easy way of making inlines orderable using drag-and-drop.
Home-page: https://github.com/marcofucci/django-inline-orderable
Author: Marco Fucci
Author-email: info@marcofucci.com
License: BSD
Platform: UNKNOWN
Classifier: Framework :: Django
Classifier: Environment :: Web Environment
Classifier: Programming Language :: Python
Classifier: Intended Audience :: Developers
Classifier: Operating System :: OS Independent
Classifier: License :: OSI Approved :: BSD License
Classifier: Topic :: Software Development :: Libraries :: Python Modules
Provides: inline_orderable
